visual_clustering/VisualClustering.py
visual_clustering/__init__.py
visual_clustering-1.0.0.dist-info/LICENSE
visual_clustering-1.0.0.dist-info/METADATA
visual_clustering-1.0.0.dist-info/WHEEL
visual_clustering-1.0.0.dist-info/top_level.txt
visual_clustering-1.0.0.dist-info/RECORD
