Metadata-Version: 2.1
Name: visual-clustering
Version: 1.0.0
Summary: An implementation of the Visual Clustering algorithm
Home-page: https://github.com/tareknaous/visual-clustering
Author: Tarek Naous
Author-email: tareknaous@gmail.com
License: UNKNOWN
Project-URL: Bug Tracker, https://github.com/tareknaous/visual-clustering
Platform: UNKNOWN
Classifier: Programming Language :: Python :: 3
Classifier: License :: OSI Approved :: MIT License
Classifier: Operating System :: OS Independent
Requires-Python: >=3.6
License-File: LICENSE
